neo_sample.py
neo_sample-0.0.1.dist-info/LICENSE
neo_sample-0.0.1.dist-info/METADATA
neo_sample-0.0.1.dist-info/WHEEL
neo_sample-0.0.1.dist-info/top_level.txt
neo_sample-0.0.1.dist-info/RECORD
