Metadata-Version: 2.1
Name: neo-sample
Version: 0.0.1
Summary: Neo-Sample Test Package
Author: Nadezhda Suraeva
License: UNKNOWN
Platform: UNKNOWN
Classifier: Programming Language :: Python :: 3
Classifier: License :: OSI Approved :: MIT License
Classifier: Operating System :: OS Independent
Requires-Python: >=3.6
License-File: LICENSE
